LICENSE
MANIFEST.in
README.md
package.json
setup.py
nx_express/__init__.py
nx_express/_imports_.py
nx_express/metadata.json
nx_express/nxExpress.py
nx_express/nx_express.min.js
nx_express/nx_express.min.js.map
nx_express/package-info.json
nx_express.egg-info/PKG-INFO
nx_express.egg-info/SOURCES.txt
nx_express.egg-info/dependency_links.txt
nx_express.egg-info/top_level.txt